log_symbols/__init__.py
log_symbols/symbols.py
frkl.log_symbols-0.0.14.dist-info/LICENSE
frkl.log_symbols-0.0.14.dist-info/METADATA
frkl.log_symbols-0.0.14.dist-info/WHEEL
frkl.log_symbols-0.0.14.dist-info/top_level.txt
frkl.log_symbols-0.0.14.dist-info/RECORD
