Metadata-Version: 1.0
Name: frkl.log_symbols
Version: 0.0.14
Summary: Colored symbols for various log levels for Python
Home-page: https://github.com/frkl-downstream/py-log-symbols
Author: Markus Binsteiner
Author-email: markus@frkl.io
License: MIT
Keywords: log symbols,symbols,log
Platform: UNKNOWN
